{
  "type": "FeatureCollection",
  "features": [
    {
      "type": "Feature",
      "properties": {
        "name": "Swift Current"
      },
      "geometry": {
        "coordinates": [
          -107.80135,
          50.28337
        ],
        "type": "Point"
      }
    }
  ]
}